{
  "project_info": {
    "project_number": "275139886228",
    "project_id": "tip-locker",
    "storage_bucket": "tip-locker.firebasestorage.app"
  },
  "client": [
    {
      "client_info": {
        "mobilesdk_app_id": "1:275139886228:android:57bbf5ef28353839340881",
        "android_client_info": {
          "package_name": "com.example.flutter_application_1"
        }
      },
      "oauth_client": [],
      "api_key": [
        {
          "current_key": "AIzaSyCILxkhQC7bmKDnlKUMdE1ZWKr72w4qSJk"
        }
      ],
      "services": {
        "appinvite_service": {
          "other_platform_oauth_client": []
        }
      }
    }
  ],
  "configuration_version": "1"
}